mapfmclient/__init__.py
mapfmclient/local_solver.py
mapfmclient/mapfbenchmarker.py
mapfmclient/parser.py
mapfmclient/problem.py
mapfmclient/solution.py
mapfmclient/status.py
mapfmclient/test_bench.py
mapfmclient/timing.py
mapfmclient-0.2.5.dist-info/LICENSE
mapfmclient-0.2.5.dist-info/METADATA
mapfmclient-0.2.5.dist-info/WHEEL
mapfmclient-0.2.5.dist-info/top_level.txt
mapfmclient-0.2.5.dist-info/RECORD
