Metadata-Version: 2.1
Name: mapfmclient
Version: 0.2.5
Summary: client library for interaction with mapf.nl
Home-page: https://github.com/jonay2000/mapfm-client
Author: Jonathan D�nszelmann
Author-email: jonabent@gmail.com
License: UNKNOWN
Project-URL: Bug Tracker, https://github.com/jonay2000/mapf_client/issues
Platform: UNKNOWN
Classifier: Programming Language :: Python :: 3
Classifier: License :: OSI Approved :: MIT License
Classifier: Operating System :: OS Independent
Requires-Python: >=3.6
Requires-Dist: requests (~=2.25.1)
Requires-Dist: pathos (~=0.2.7)
Requires-Dist: tqdm (~=4.60.0)
Requires-Dist: func-timeout (~=4.3.5)
